[
  {
    "id": "MA_2_0",
    "name": "طرقة رياضة الدور الثاني",
    "type": "طرقة",
    "style": {
      "font-size": "14px"
    },
    "images": []
  },
  {
    "id": "MA_2_1",
    "name": "د/سامي عبدالفتاح العطار|د/عاطف البنداري",
    "type": "مكتب",
    "style": {
      "font-size": "14px"
    },
    "images": []
  },
  {
    "id": "MA_2_2",
    "name": "د/هاني على الغرباوى|د/أيمن موسى الطحان|د/محمد مجدي الشهاوى",
    "type": "مكتب",
    "style": {
      "font-size": "14px"
    },
    "images": []
  },
  {
    "id": "MA_2_3",
    "name": "د/ابراهيم عثمان|د/محمود محمد على|د/صلاح عزت الزهرى|د/احمد حماد عامر|د/حسن جاد الحق الجوهري|أ.د/رضا مرسى",
    "type": "مكتب",
    "style": {
      "font-size": "14px"
    },
    "images": []
  },  
  {
    "id": "MA_2_4",
    "name": "د/سماح مبروك|د/ايناس حسن الغزاوى/جيهان فتح الله عبادالله|د/فاطمة الزهراء احمد ابو الأسعاد",
    "type": "مكتب",
    "style": {
      "font-size": "14px"
    },
    "images": []
  },
  {
    "id": "MA_2_5",
    "name": "د/دلال محمد حميده|د/ماجدة ذكي سعيد|د/مها مصطفى",
    "type": "مكتب",
    "style": {
      "font-size": "14px"
    },
    "images": []
  },
  {
    "id": "MA_2_6",
    "name": "د/مها خالد عمر|أ.د/خالد محمد ابو المعاطى عمر|أ.د/سلوى سعد",
    "type": "مكتب",
    "style": {
      "font-size": "14px"
    },
    "images": []
  },
  {
    "id": "MA_2_7",
    "name": "أ.د/ضحى القونى|د/أمينة ابراهيم غنيم|د/نجوى عبدالمنعم",
    "type": "مكتب",
    "style": {
      "font-size": "14px"
    },
    "images": []
  },
  {
    "id": "MA_2_8",
    "name": "حمام طلاب",
    "type": "حمام",
    "style": {
      "font-size": "14px"
    },
    "images": []
  },
  {
    "id": "MA_2_9",
    "name": "حمام طالبات",
    "type": "حمام",
    "style": {
      "font-size": "14px"
    },
    "images": []
  },
  {
    "id": "MA_2_10",
    "name": "أ.د/عادل الشنشورى|د/سلوى فهمي بدر",
    "type": "مكتب",
    "style": {
      "font-size": "14px"
    },
    "images": []
  },    
  {
    "id": "MA_2_11",
    "name": "أ.د/رضا سمور|د/محمد احمد العيسوى|د/محمد موسى ميره|د/محمد على احمد عيد",
    "type": "مكتب",
    "style": {
      "font-size": "14px"
    },
    "images": []
  },
  {
    "id": "MA_2_12",
    "name": "أ.د/وجيه الشونى|د/حنان محمود|د/بريهان صالح عطية|د/هدى شوقي نوح",
    "type": "مكتب",
    "style": {
      "font-size": "14px"
    },
    "images": []
  },
  {
    "id": "MA_2_13",
    "name": "أ.د/عواطف محسن|د/هبة بدير",
    "type": "مكتب",
    "style": {
      "font-size": "14px"
    },
    "images": []
  },
  {
    "id": "MA_2_14",
    "name": "أ.د/كمال شلتوت|د/عبدالفتاح ابو مهره|د/سلمى شلتوت",
    "type": "مكتب",
    "style": {
      "font-size": "14px"
    },
    "images": []
  },
  {
    "id": "MA_2_15",
    "name": "د/ايمان عبدالظاهر|د/نانيس جمال الدين|د/شيماء حمدي|د/سالي متولي",
    "type": "مكتب",
    "style": {
      "font-size": "14px"
    },
    "images": []
  },
  {
    "id": "MA_2_16",
    "name": "أ.د/عصام عزب|د/سامية شبانة|د/سامح سمير على|د/ايناس مصطفى البلاط|أ.د/مها محمود عزب",
    "type": "مكتب",
    "style": {
      "font-size": "14px"
    },
    "images": []
  },
  {
    "id": "MA_2_17",
    "name": "د/محسن كمال حسن ابراهيم|د/محمد لطفى حلاوة",
    "type": "مكتب",
    "style": {
      "font-size": "14px"
    },
    "images": []
  },
  {
    "id": "BIO_2_0",
    "name": "طرقة مبنى بيولوجي الدور الثاني",
    "type": "طرقة",
    "style": {
      "font-size": "14px"
    },
    "images": []
  },
  {
    "id": "BIO_2_1",
    "name": "حمام طلاب",
    "type": "حمام",
    "style": {
      "font-size": "14px"
    },
    "images": []
  },
  {
    "id": "BIO_2_2",
    "name": "حمام طالبات",
    "type": "حمام",
    "style": {
      "font-size": "14px"
    },
    "images": []
  },
  {
    "id": "BIO_2_3",
    "name": "أ.د/يحيي عبدالجليل|أ.د/نسمه الزواوى",
    "type": "مكتب",
    "style": {
      "font-size": "14px"
    },
    "images": []
  },
  {
    "id": "BIO_2_4",
    "name": "أ.د/أشرف حيدر|أ.د/رضا جعفر",
    "type": "مكتب",
    "style": {
      "font-size": "14px"
    },
    "images": []
  },
  {
    "id": "BIO_2_5",
    "name": "أ.د/أمل النجار|أ.د/شيماء الشافعي",
    "type": "مكتب",
    "style": {
      "font-size": "14px"
    },
    "images": []
  },
  {
    "id": "BIO_2_6",
    "name": "أ.د/عاطف أبو شادي|أ.د/جيهان اسماعيل",
    "type": "مكتب",
    "style": {
      "font-size": "14px"
    },
    "images": []
  },
  
  {
    "id": "BIO_2_7",
    "name": "أ.د/علاء أبوزيد|أ.د/متولي عبدالعظيم",
    "type": "مكتب",
    "style": {
      "font-size": "14px"
    },
    "images": []
  }, 
  {
    "id": "BIO_2_8",
    "name": "أ.د/عبدالرحيم الشنشورى|أ.د/صبحي الصاوى",
    "type": "مكتب",
    "style": {
      "font-size": "14px"
    },
    "images": []
  },
  {
    "id": "BIO_2_9",
    "name": "أ.د/أميمة عوض الله|أ.د/ياسر بديوى",
    "type": "مكتب",
    "style": {
      "font-size": "14px"
    },
    "images": []
  },
  {
    "id": "BIO_2_10",
    "name": "أ.د/ايمان عبدالظاهر|أ.د/سالي غيده",
    "type": "مكتب",
    "style": {
      "font-size": "14px"
    },
    "images": []
  },
  {
    "id": "BIO_2_11",
    "name": "أ.د/داليا عبدالعظيم|أ.د/مها خليل",
    "type": "مكتب",
    "style": {
      "font-size": "14px"
    },
    "images": []
  },
  {
    "id": "BIO_2_12",
    "name": "أ.د/مصطفى الشيخ",
    "type": "مكتب",
    "style": {
      "font-size": "14px"
    },
    "images": []
  },
  {
    "id": "BIO_2_13",
    "name": "قسم النبات والميكروبيولوجي المعشبة",
    "type": "معمل",
    "style": {
      "font-size": "14px"
    },
    "images": []
  },
  {
    "id": "BIO_2_14",
    "name": "مكتب سكرتارية القسم",
    "type": "مكتب",
    "style": {
      "font-size": "14px"
    },
    "images": []
  },
  {
    "id": "BIO_2_15",
    "name": "رئيس مجلس القسم",
    "type": "مكتب",
    "style": {
      "font-size": "14px"
    },
    "images": []
  },
  {
    "id": "BIO_2_16",
    "name": "معمل أبحاث الفطريات",
    "type": "معمل",
    "style": {
      "font-size": "14px"
    },
    "images": []
  },
  {
    "id": "BIO_2_17",
    "name": "معمل طلاب رقم (2)",
    "type": "معمل",
    "style": {
      "font-size": "14px"
    },
    "images": []
  },
  {
    "id": "BIO_2_18",
    "name": "معمل أبحاث البكتريا",
    "type": "معمل",
    "style": {
      "font-size": "14px"
    },
    "images": []
  },
  {
    "id": "BIO_2_19",
    "name": "معمل أبحاث الطحالب",
    "type": "معمل",
    "style": {
      "font-size": "14px"
    },
    "images": []
  },
  {
    "id": "BIO_2_20",
    "name": "معمل طلاب رقم (1)",
    "type": "معمل",
    "style": {
      "font-size": "14px"
    },
    "images": []
  },
  {
    "id": "BIO_2_21",
    "name": "مدرج (5)",
    "type": "مدرج",
    "style": {
      "font-size": "14px"
    },
    "images": []
  },
  {
    "id": "BIO_2_22",
    "name": " معمل (7)|قاعة السمينار",
    "type": "معمل",
    "style": {
      "font-size": "14px"
    },
    "images": []
  },
  {
    "id": "GEO_2_0",
    "name": "طرقة مبنى جيو الدور الثاني",
    "type": "طرقة",
    "style": {
      "font-size": "14px"
    },
    "images": []
  },
  {
    "id": "GEO_2_1",
    "name": "حمام طلاب",
    "type": "حمام",
    "style": {
      "font-size": "14px"
    },
    "images": []
  },
  {
    "id": "GEO_2_2",
    "name": "حمام طالبات",
    "type": "حمام",
    "style": {
      "font-size": "14px"
    },
    "images": []
  },
  {
    "id": "GEO_2_3",
    "name": "أ.د/نبيل محمد السراجي|أ.د/ايمان نبيل السراجي|أ.د/ايه رضا البدوى",
    "type": "مكتب",
    "style": {
      "font-size": "14px"
    },
    "images": []
  },
  {
    "id": "GEO_2_4",
    "name": "أ.د/محمد رأفت اسماعيل رمضان|د/على عبدالسلام",
    "type": "مكتب",
    "style": {
      "font-size": "14px"
    },
    "images": []
  },
  {
    "id": "GEO_2_5",
    "name": "أ.د/أبو الحسن شفيق سعود|أ.د/بهجت يوسف البرادعى",
    "type": "مكتب",
    "style": {
      "font-size": "14px"
    },
    "images": []
  },
  {
    "id": "GEO_2_6",
    "name": "أ.د/حسنين محمد اللباني|أ.د/عبدالرازق عابدين|أ.د/رياض محمد غازى",
    "type": "مكتب",
    "style": {
      "font-size": "14px"
    },
    "images": []
  },
  {
    "id": "GEO_2_7",
    "name": "أ.د/محمود مصطفى كامل|أ.د/سعد الدين ابراهيم ابو العينين|أ.د/محمد النجار",
    "type": "مكتب",
    "style": {
      "font-size": "14px"
    },
    "images": []
  },
  {
    "id": "GEO_2_8",
    "name": "أ.د/جاب الله عبدالستار جاب الله|أ.د/حسن عبدالقادر الكاشف|د/سامي عبدالقادر",
    "type": "مكتب",
    "style": {
      "font-size": "14px"
    },
    "images": []
  },
  {
    "id": "GEO_2_9",
    "name": "قاعة الأجتماعات",
    "type": "قاعة",
    "style": {
      "font-size": "14px"
    },
    "images": []
  },
  {
    "id": "GEO_2_10",
    "name": "سكرتاريه",
    "type": "ادارة",
    "style": {
      "font-size": "14px"
    },
    "images": []
  },
  {
    "id": "GEO_2_11",
    "name": "رئيس القسم",
    "type": "ادارة",
    "style": {
      "font-size": "14px"
    },
    "images": []
  },
  {
    "id": "GEO_2_12",
    "name": "معامل الفرقة الأولى (ب)",
    "type": "معمل",
    "style": {
      "font-size": "14px"
    },
    "images": []
  },
  {
    "id": "GEO_2_13",
    "name": "معمل السنوات الأولى|معمل الضوء",
    "type": "معمل",
    "style": {
      "font-size": "14px"
    },
    "images": []
  },
  {
    "id": "GEO_2_14",
    "name": "معمل تحضير المواد النانومترية والمتراكبات",
    "type": "معمل",
    "style": {
      "font-size": "14px"
    },
    "images": []
  },
  {
    "id": "GEO_2_15",
    "name": "معامل الفرقة الأولى (أ)",
    "type": "معمل",
    "style": {
      "font-size": "14px"
    },
    "images": []
  },
   {
    "id": "GEO_2_16",
    "name": "معمل الفيزياء النظرية والمحاكاه",
    "type": "معمل",
    "style": {
      "font-size": "14px"
    },
    "images": []
  },
   {
    "id": "GEO_2_17",
    "name": "مدرج (1)",
    "type": "مدرج",
    "style": {
      "font-size": "14px"
    },
    "images": []
  },
  {
    "id": "CH_2_0",
    "name": "طرقة مبنى كيمياء الدور الثاني",
    "type": "طرقة",
    "style": {
      "font-size": "14px"
    },
    "images": []
  },
  {
    "id": "CH_2_1",
    "name": "المخزن",
    "type": "مخزن",
    "style": {
      "font-size": "14px"
    },
    "images": []
  },
  {
    "id": "CH_2_2",
    "name": "معمل فيزياء البلازما",
    "type": "معمل",
    "style": {
      "font-size": "14px"
    },
    "images": []
  },
  {
    "id": "CH_2_3",
    "name": "معمل الفيزياء الحيوية",
    "type": "معمل",
    "style": {
      "font-size": "14px"
    },
    "images": []
  },
  {
    "id": "CH_2_4",
    "name": "أ.د/أسامة محمد حميدة",
    "type": "مكتب",
    "style": {
      "font-size": "14px"
    },
    "images": []
  },
  {
    "id": "CH_2_5",
    "name": "د/شريف حمادة|د/أحمد ماهر حنيش|أحمد عمار",
    "type": "مكتب",
    "style": {
      "font-size": "14px"
    },
    "images": []
  },
  {
    "id": "CH_2_6",
    "name": "أ.د/فاروق مصطفى المكاوى|د/أحمد فاروق المكاوى",
    "type": "مكتب",
    "style": {
      "font-size": "14px"
    },
    "images": []
  },
  {
    "id": "CH_2_7",
    "name": "أ.د/حسين محمود بدران|أ.د/فتحي أحمدالحسيني",
    "type": "مكتب",
    "style": {
      "font-size": "14px"
    },
    "images": []
  },
  {
    "id": "CH_2_8",
    "name": "أ.د/محسن بركات|د/جمال أبو قورة|د/مصطفى الطحاوى|د/محمد حمزه بدوى|د/أحمد سعيد عتلم",
    "type": "مكتب",
    "style": {
      "font-size": "14px"
    },
    "images": []
  },
  {
    "id": "CH_2_9",
    "name": "أ.د/مصطفى كمال النمر|د/سامية أحمد سعفان",
    "type": "مكتب",
    "style": {
      "font-size": "14px"
    },
    "images": []
  },
  {
    "id": "CH_2_10",
    "name": "حمام الدكاترة",
    "type": "حمام",
    "style": {
      "font-size": "14px"
    },
    "images": []
  },
  {
    "id": "CH_2_11",
    "name": "أ.د/عبدالرؤف توفيق|د/بسنت ابراهيم عبدالناجي سالم|د/فاطمة الزهراء فخرى",
    "type": "مكتب",
    "style": {
      "font-size": "14px"
    },
    "images": []
  },
  {
    "id": "CH_2_12",
    "name": "قاعة المناظرات|مدرج(9)",
    "type": "قاعة",
    "style": {
      "font-size": "14px"
    },
    "images": []
  },
  {
    "id": "CH_2_13",
    "name": "معمل أبحاث الالكترونيات وعلوم المواد",
    "type": "معمل",
    "style": {
      "font-size": "14px"
    },
    "images": []
  },
  {
    "id": "CH_2_14",
    "name": "معمل التحليل الاشعاعي",
    "type": "معمل",
    "style": {
      "font-size": "14px"
    },
    "images": []
  },
  {
    "id": "CH_2_15",
    "name": "معمل أبحاث الجوامد",
    "type": "معمل",
    "style": {
      "font-size": "14px"
    },
    "images": []
  },
  {
    "id": "CH_2_16",
    "name": "معمل أبحاث الطاقة الشمسية",
    "type": "معمل",
    "style": {
      "font-size": "14px"
    },
    "images": []
  },
  {
    "id": "CH_2_17",
    "name": "Enzymology Lab",
    "type": "معمل",
    "style": {
      "font-size": "14px"
    },
    "images": []
  },
  {
    "id": "CH_2_18",
    "name": "Molecular Proteomics Lab",
    "type": "معمل",
    "style": {
      "font-size": "14px"
    },
    "images": []
  },
  {
    "id": "stairs_2_1",
    "name": "سلم جيو الدور الثاني",
    "type": "سلم",
    "style": {
      "font-size": "14px"
    },
    "images": []
  },
    {
    "id": "x_stairs_2_1",
    "name": "سلم مبنى الاداره",
    "type": "سلم",
    "style": {
      "font-size": "14px"
    },
    "images": []
  },
      {
    "id": "x_stairs_2_2",
    "name": "سلم مبنى الاداره",
    "type": "سلم",
    "style": {
      "font-size": "14px"
    },
    "images": []
  },
  {
    "id": "stairs_2_2",
    "name": "سلم بايو الدور الثاني",
    "type": "سلم",
    "style": {
      "font-size": "14px"
    },
    "images": []
  },
   {
    "id": "stairs_2_3",
    "name": "سلم بايو كيميا الدور الثاني",
    "type": "سلم",
    "style": {
      "font-size": "14px"
    },
    "images": []
  },
  {
    "id": "stairs_2_4",
    "name": "سلم جيو كيميا الدور الثاني",
    "type": "سلم",
    "style": {
      "font-size": "14px"
    },
    "images": []
  },
  {
    "id": "stairs_2_5",
    "name": "سلم كيمياء الدور الثاني",
    "type": "سلم",
    "style": {
      "font-size": "14px"
    },
    "images": []
  },
  {
    "id": "elevator_2_1",
    "name": "اسانسير جيو الدور الثاني",
    "type": "مصعد",
    "style": {
      "font-size": "14px"
    },
    "images": []
  },
  {
    "id": "elevator_2_2",
    "name": "اسانسير بايو الدور الثاني",
    "type": "مصعد",
    "style": {
      "font-size": "14px"
    },
    "images": []
  },
  {
    "id": "elevator_2_3",
    "name": "اسانسير بايو كيميا الدور الثاني",
    "type": "مصعد",
    "style": {
      "font-size": "14px"
    },
    "images": []
  },
  {
    "id": "elevator_2_4",
    "name": "اسانسير جيو كيميا الدور الثاني",
    "type": "مصعد",
    "style": {
      "font-size": "14px"
    },
    "images": []
  },
  {
    "id": "nexus_2_1",
    "name": "صالة جيو الدور الثاني",
    "type": "صالة",
    "style": {
      "font-size": "14px"
    },
    "images": []
  },
  {
    "id": "nexus_2_2",
    "name": "صالة بايو الدور الثاني",
    "type": "صالة",
    "style": {
      "font-size": "14px"
    },
    "images": []
  },
  {
    "id": "nexus_2_3",
    "name": "طرقة بايو كيميا الدور الثاني",
    "type": "طرقة",
    "style": {
      "font-size": "14px"
    },
    "images": []
  },
  {
    "id": "nexus_2_4",
    "name": "صالة كيمياء الدور الثاني",
    "type": "صالة",
    "style": {
      "font-size": "14px"
    },
    "images": []
  },
  {
    "id": "nexus_2_5",
    "name": "طرقة جيو كيميا الدور الثاني",
    "type": "طرقة",
    "style": {
      "font-size": "14px"
    },
    "images": []
  },
  {
    "id": "stairs_2_6",
    "name": "سلم الدور الثانى",
    "type": "سلم",
    "style": {
      "font-size": "14px"
    },
    "images": []
  },
  {
    "id": "stairs_2_7",
    "name": "سلم الدور الثانى",
    "type": "سلم",
    "style": {
      "font-size": "14px"
    },
    "images": []
  },
  {
    "id": "x_Lnd_2_1",
    "name": "طرقة الدور الثانى",
    "type": "طرقة",
    "style": {
      "font-size": "14px"
    },
    "images": []
  },
  {
    "id": "x_Lnd_2_2",
    "name": "طرقة الدور الثانى",
    "type": "طرقة",
    "style": {
      "font-size": "14px"
    },
    "images": []
  },
  {
    "id": "x_B1_2_1",
    "name": "المكتبة",
    "type": "ادارة",
    "style": {
      "font-size": "14px"
    },
    "images": []
  }
]
  